[
  {
    "Id": 1,
    "Code": "AFG",
    "Name": "Afghanistan"
  },
  {
    "Id": 2,
    "Code": "ALB",
    "Name": "Albania"
  },
  {
    "Id": 3,
    "Code": "ALG",
    "Name": "Algeria"
  },
  {
    "Id": 4,
    "Code": "ASA",
    "Name": "American Samoa"
  },
  {
    "Id": 5,
    "Code": "AND",
    "Name": "Andorra"
  },
  {
    "Id": 6,
    "Code": "ANG",
    "Name": "Angola"
  },
  {
    "Id": 9,
    "Code": "ANT",
    "Name": "Antigua and Barbuda"
  },
  {
    "Id": 10,
    "Code": "ARG",
    "Name": "Argentina"
  },
  {
    "Id": 11,
    "Code": "ARM",
    "Name": "Armenia"
  },
  {
    "Id": 12,
    "Code": "ARU",
    "Name": "Aruba"
  },
  {
    "Id": 13,
    "Code": "AUS",
    "Name": "Australia"
  },
  {
    "Id": 14,
    "Code": "AUT",
    "Name": "Austria"
  },
  {
    "Id": 15,
    "Code": "AZE",
    "Name": "Azerbaijan"
  },
  {
    "Id": 16,
    "Code": "BAH",
    "Name": "Bahamas"
  },
  {
    "Id": 17,
    "Code": "BRN",
    "Name": "Bahrain"
  },
  {
    "Id": 18,
    "Code": "BAN",
    "Name": "Bangladesh"
  },
  {
    "Id": 19,
    "Code": "BAR",
    "Name": "Barbados"
  },
  {
    "Id": 20,
    "Code": "BLR",
    "Name": "Belarus"
  },
  {
    "Id": 21,
    "Code": "BEL",
    "Name": "Belgium"
  },
  {
    "Id": 22,
    "Code": "BIZ",
    "Name": "Belize"
  },
  {
    "Id": 23,
    "Code": "BEN",
    "Name": "Benin"
  },
  {
    "Id": 24,
    "Code": "BER",
    "Name": "Bermuda"
  },
  {
    "Id": 25,
    "Code": "BHU",
    "Name": "Bhutan"
  },
  {
    "Id": 26,
    "Code": "BOL",
    "Name": "Bolivia"
  },
  {
    "Id": 250,
    "Code": "BES",
    "Name": "Bonaire, Sint Eustatius and Saba"
  },
  {
    "Id": 27,
    "Code": "BIH",
    "Name": "Bosnia and Herzegovina"
  },
  {
    "Id": 28,
    "Code": "BOT",
    "Name": "Botswana"
  },
  {
    "Id": 30,
    "Code": "BRA",
    "Name": "Brazil"
  },
  {
    "Id": 32,
    "Code": "BRU",
    "Name": "Brunei Darussalam"
  },
  {
    "Id": 33,
    "Code": "BUL",
    "Name": "Bulgaria"
  },
  {
    "Id": 34,
    "Code": "BUR",
    "Name": "Burkina Faso"
  },
  {
    "Id": 35,
    "Code": "BDI",
    "Name": "Burundi"
  },
  {
    "Id": 36,
    "Code": "CAM",
    "Name": "Cambodia"
  },
  {
    "Id": 37,
    "Code": "CMR",
    "Name": "Cameroon"
  },
  {
    "Id": 38,
    "Code": "CAN",
    "Name": "Canada"
  },
  {
    "Id": 39,
    "Code": "CPV",
    "Name": "Cape Verde"
  },
  {
    "Id": 40,
    "Code": "CAY",
    "Name": "Cayman Islands"
  },
  {
    "Id": 41,
    "Code": "CAF",
    "Name": "Central African Republic"
  },
  {
    "Id": 42,
    "Code": "CHA",
    "Name": "Chad"
  },
  {
    "Id": 43,
    "Code": "CHI",
    "Name": "Chile"
  },
  {
    "Id": 44,
    "Code": "CHN",
    "Name": "China"
  },
  {
    "Id": 47,
    "Code": "COL",
    "Name": "Colombia"
  },
  {
    "Id": 48,
    "Code": "COM",
    "Name": "Comoros"
  },
  {
    "Id": 49,
    "Code": "CGO",
    "Name": "Congo"
  },
  {
    "Id": 50,
    "Code": "COD",
    "Name": "Congo, The Democratic Republic of the"
  },
  {
    "Id": 51,
    "Code": "COK",
    "Name": "Cook Islands"
  },
  {
    "Id": 52,
    "Code": "CRC",
    "Name": "Costa Rica"
  },
  {
    "Id": 53,
    "Code": "CIV",
    "Name": "C\u00F4te d\u0027Ivoire"
  },
  {
    "Id": 54,
    "Code": "CRO",
    "Name": "Croatia"
  },
  {
    "Id": 55,
    "Code": "CUB",
    "Name": "Cuba"
  },
  {
    "Id": 248,
    "Code": "CUW",
    "Name": "Cura\u00E7ao"
  },
  {
    "Id": 56,
    "Code": "CYP",
    "Name": "Cyprus"
  },
  {
    "Id": 57,
    "Code": "CZE",
    "Name": "Czech Republic"
  },
  {
    "Id": 58,
    "Code": "DEN",
    "Name": "Denmark"
  },
  {
    "Id": 59,
    "Code": "DJI",
    "Name": "Djibouti"
  },
  {
    "Id": 60,
    "Code": "DMA",
    "Name": "Dominica"
  },
  {
    "Id": 61,
    "Code": "DOM",
    "Name": "Dominican Republic"
  },
  {
    "Id": 62,
    "Code": "ECU",
    "Name": "Ecuador"
  },
  {
    "Id": 63,
    "Code": "EGY",
    "Name": "Egypt"
  },
  {
    "Id": 64,
    "Code": "ESA",
    "Name": "El Salvador"
  },
  {
    "Id": 65,
    "Code": "GEQ",
    "Name": "Equatorial Guinea"
  },
  {
    "Id": 66,
    "Code": "ERI",
    "Name": "Eritrea"
  },
  {
    "Id": 67,
    "Code": "EST",
    "Name": "Estonia"
  },
  {
    "Id": 68,
    "Code": "ETH",
    "Name": "Ethiopia"
  },
  {
    "Id": 69,
    "Code": "FLK",
    "Name": "Falkland Islands (Malvinas)"
  },
  {
    "Id": 70,
    "Code": "FRO",
    "Name": "Faroe Islands"
  },
  {
    "Id": 71,
    "Code": "FIJ",
    "Name": "Fiji"
  },
  {
    "Id": 72,
    "Code": "FIN",
    "Name": "Finland"
  },
  {
    "Id": 73,
    "Code": "FRA",
    "Name": "France"
  },
  {
    "Id": 74,
    "Code": "GUF",
    "Name": "French Guiana"
  },
  {
    "Id": 75,
    "Code": "PYF",
    "Name": "French Polynesia"
  },
  {
    "Id": 77,
    "Code": "GAB",
    "Name": "Gabon"
  },
  {
    "Id": 78,
    "Code": "GAM",
    "Name": "Gambia"
  },
  {
    "Id": 79,
    "Code": "GEO",
    "Name": "Georgia"
  },
  {
    "Id": 80,
    "Code": "GER",
    "Name": "Germany"
  },
  {
    "Id": 81,
    "Code": "GHA",
    "Name": "Ghana"
  },
  {
    "Id": 82,
    "Code": "GIB",
    "Name": "Gibraltar"
  },
  {
    "Id": 83,
    "Code": "GRE",
    "Name": "Greece"
  },
  {
    "Id": 84,
    "Code": "GRL",
    "Name": "Greenland"
  },
  {
    "Id": 85,
    "Code": "GRN",
    "Name": "Grenada"
  },
  {
    "Id": 86,
    "Code": "GLP",
    "Name": "Guadeloupe"
  },
  {
    "Id": 87,
    "Code": "GUM",
    "Name": "Guam"
  },
  {
    "Id": 88,
    "Code": "GUA",
    "Name": "Guatemala"
  },
  {
    "Id": 89,
    "Code": "GUI",
    "Name": "Guinea"
  },
  {
    "Id": 90,
    "Code": "GBS",
    "Name": "Guinea-Bissau"
  },
  {
    "Id": 91,
    "Code": "GUY",
    "Name": "Guyana"
  },
  {
    "Id": 92,
    "Code": "HAI",
    "Name": "Haiti"
  },
  {
    "Id": 94,
    "Code": "VAT",
    "Name": "Holy See (Vatican City State)"
  },
  {
    "Id": 95,
    "Code": "HON",
    "Name": "Honduras"
  },
  {
    "Id": 96,
    "Code": "HKG",
    "Name": "Hong Kong"
  },
  {
    "Id": 97,
    "Code": "HUN",
    "Name": "Hungary"
  },
  {
    "Id": 98,
    "Code": "ISL",
    "Name": "Iceland"
  },
  {
    "Id": 99,
    "Code": "IND",
    "Name": "India"
  },
  {
    "Id": 100,
    "Code": "INA",
    "Name": "Indonesia"
  },
  {
    "Id": 101,
    "Code": "IRI",
    "Name": "Iran, Islamic Republic of"
  },
  {
    "Id": 102,
    "Code": "IRQ",
    "Name": "Iraq"
  },
  {
    "Id": 103,
    "Code": "IRL",
    "Name": "Ireland"
  },
  {
    "Id": 104,
    "Code": "ISR",
    "Name": "Israel"
  },
  {
    "Id": 105,
    "Code": "ITA",
    "Name": "Italy"
  },
  {
    "Id": 106,
    "Code": "JAM",
    "Name": "Jamaica"
  },
  {
    "Id": 107,
    "Code": "JPN",
    "Name": "Japan"
  },
  {
    "Id": 108,
    "Code": "JOR",
    "Name": "Jordan"
  },
  {
    "Id": 109,
    "Code": "KAZ",
    "Name": "Kazakhstan"
  },
  {
    "Id": 110,
    "Code": "KEN",
    "Name": "Kenya"
  },
  {
    "Id": 111,
    "Code": "KIR",
    "Name": "Kiribati"
  },
  {
    "Id": 112,
    "Code": "PRK",
    "Name": "Korea, Democratic People\u0027s Republic of"
  },
  {
    "Id": 113,
    "Code": "KOR",
    "Name": "Korea, Republic of"
  },
  {
    "Id": 114,
    "Code": "KUW",
    "Name": "Kuwait"
  },
  {
    "Id": 115,
    "Code": "KGZ",
    "Name": "Kyrgyzstan"
  },
  {
    "Id": 116,
    "Code": "LAO",
    "Name": "Lao People\u0027s Democratic Republic"
  },
  {
    "Id": 117,
    "Code": "LAT",
    "Name": "Latvia"
  },
  {
    "Id": 118,
    "Code": "LIB",
    "Name": "Lebanon"
  },
  {
    "Id": 119,
    "Code": "LES",
    "Name": "Lesotho"
  },
  {
    "Id": 120,
    "Code": "LBR",
    "Name": "Liberia"
  },
  {
    "Id": 121,
    "Code": "LBA",
    "Name": "Libya"
  },
  {
    "Id": 122,
    "Code": "LIE",
    "Name": "Liechtenstein"
  },
  {
    "Id": 123,
    "Code": "LTU",
    "Name": "Lithuania"
  },
  {
    "Id": 124,
    "Code": "LUX",
    "Name": "Luxembourg"
  },
  {
    "Id": 125,
    "Code": "MAC",
    "Name": "Macao"
  },
  {
    "Id": 126,
    "Code": "MKD",
    "Name": "Macedonia"
  },
  {
    "Id": 127,
    "Code": "MAD",
    "Name": "Madagascar"
  },
  {
    "Id": 128,
    "Code": "MAW",
    "Name": "Malawi"
  },
  {
    "Id": 129,
    "Code": "MAS",
    "Name": "Malaysia"
  },
  {
    "Id": 130,
    "Code": "MDV",
    "Name": "Maldives"
  },
  {
    "Id": 131,
    "Code": "MLI",
    "Name": "Mali"
  },
  {
    "Id": 132,
    "Code": "MLT",
    "Name": "Malta"
  },
  {
    "Id": 133,
    "Code": "MHL",
    "Name": "Marshall Islands"
  },
  {
    "Id": 134,
    "Code": "MTQ",
    "Name": "Martinique"
  },
  {
    "Id": 135,
    "Code": "MTN",
    "Name": "Mauritania"
  },
  {
    "Id": 136,
    "Code": "MRI",
    "Name": "Mauritius"
  },
  {
    "Id": 137,
    "Code": "MYT",
    "Name": "Mayotte"
  },
  {
    "Id": 138,
    "Code": "MEX",
    "Name": "Mexico"
  },
  {
    "Id": 139,
    "Code": "FSM",
    "Name": "Micronesia, Federated States of"
  },
  {
    "Id": 140,
    "Code": "MDA",
    "Name": "Moldova"
  },
  {
    "Id": 141,
    "Code": "MON",
    "Name": "Monaco"
  },
  {
    "Id": 142,
    "Code": "MGL",
    "Name": "Mongolia"
  },
  {
    "Id": 143,
    "Code": "MNE",
    "Name": "Montenegro"
  },
  {
    "Id": 145,
    "Code": "MAR",
    "Name": "Morocco"
  },
  {
    "Id": 146,
    "Code": "MOZ",
    "Name": "Mozambique"
  },
  {
    "Id": 147,
    "Code": "MYA",
    "Name": "Myanmar"
  },
  {
    "Id": 148,
    "Code": "NAM",
    "Name": "Namibia"
  },
  {
    "Id": 149,
    "Code": "NRU",
    "Name": "Nauru"
  },
  {
    "Id": 150,
    "Code": "NEP",
    "Name": "Nepal"
  },
  {
    "Id": 151,
    "Code": "NED",
    "Name": "Netherlands"
  },
  {
    "Id": 153,
    "Code": "NCL",
    "Name": "New Caledonia"
  },
  {
    "Id": 154,
    "Code": "NZL",
    "Name": "New Zealand"
  },
  {
    "Id": 155,
    "Code": "NCA",
    "Name": "Nicaragua"
  },
  {
    "Id": 156,
    "Code": "NIG",
    "Name": "Niger"
  },
  {
    "Id": 157,
    "Code": "NGR",
    "Name": "Nigeria"
  },
  {
    "Id": 159,
    "Code": "NFK",
    "Name": "Norfolk Island"
  },
  {
    "Id": 161,
    "Code": "NOR",
    "Name": "Norway"
  },
  {
    "Id": 162,
    "Code": "OMA",
    "Name": "Oman"
  },
  {
    "Id": 163,
    "Code": "PAK",
    "Name": "Pakistan"
  },
  {
    "Id": 164,
    "Code": "PLW",
    "Name": "Palau"
  },
  {
    "Id": 165,
    "Code": "PLE",
    "Name": "Palestine"
  },
  {
    "Id": 166,
    "Code": "PAN",
    "Name": "Panama"
  },
  {
    "Id": 167,
    "Code": "PNG",
    "Name": "Papua New Guinea"
  },
  {
    "Id": 168,
    "Code": "PAR",
    "Name": "Paraguay"
  },
  {
    "Id": 169,
    "Code": "PER",
    "Name": "Peru"
  },
  {
    "Id": 170,
    "Code": "PHI",
    "Name": "Philippines"
  },
  {
    "Id": 171,
    "Code": "PCN",
    "Name": "Pitcairn"
  },
  {
    "Id": 172,
    "Code": "POL",
    "Name": "Poland"
  },
  {
    "Id": 173,
    "Code": "POR",
    "Name": "Portugal"
  },
  {
    "Id": 174,
    "Code": "PUR",
    "Name": "Puerto Rico"
  },
  {
    "Id": 175,
    "Code": "QAT",
    "Name": "Qatar"
  },
  {
    "Id": 176,
    "Code": "REU",
    "Name": "R\u00E9union"
  },
  {
    "Id": 177,
    "Code": "ROU",
    "Name": "Romania"
  },
  {
    "Id": 178,
    "Code": "RUS",
    "Name": "Russian Federation"
  },
  {
    "Id": 179,
    "Code": "RWA",
    "Name": "Rwanda"
  },
  {
    "Id": 181,
    "Code": "SKN",
    "Name": "Saint Kitts and Nevis"
  },
  {
    "Id": 182,
    "Code": "LCA",
    "Name": "Saint Lucia"
  },
  {
    "Id": 184,
    "Code": "VIN",
    "Name": "Saint Vincent and the Grenadines"
  },
  {
    "Id": 185,
    "Code": "SAM",
    "Name": "Samoa"
  },
  {
    "Id": 186,
    "Code": "SMR",
    "Name": "San Marino"
  },
  {
    "Id": 187,
    "Code": "STP",
    "Name": "S\u00E3o Tom\u00E9 and Pr\u00EDncipe"
  },
  {
    "Id": 188,
    "Code": "KSA",
    "Name": "Saudi Arabia"
  },
  {
    "Id": 189,
    "Code": "SEN",
    "Name": "Senegal"
  },
  {
    "Id": 190,
    "Code": "SRB",
    "Name": "Serbia"
  },
  {
    "Id": 191,
    "Code": "SEY",
    "Name": "Seychelles"
  },
  {
    "Id": 192,
    "Code": "SLE",
    "Name": "Sierra Leone"
  },
  {
    "Id": 193,
    "Code": "SIN",
    "Name": "Singapore"
  },
  {
    "Id": 249,
    "Code": "SXM",
    "Name": "Sint Maarten"
  },
  {
    "Id": 194,
    "Code": "SVK",
    "Name": "Slovakia"
  },
  {
    "Id": 195,
    "Code": "SLO",
    "Name": "Slovenia"
  },
  {
    "Id": 196,
    "Code": "SOL",
    "Name": "Solomon Islands"
  },
  {
    "Id": 197,
    "Code": "SOM",
    "Name": "Somalia"
  },
  {
    "Id": 198,
    "Code": "RSA",
    "Name": "South Africa"
  },
  {
    "Id": 202,
    "Code": "SSD",
    "Name": "South Sudan"
  },
  {
    "Id": 200,
    "Code": "ESP",
    "Name": "Spain"
  },
  {
    "Id": 201,
    "Code": "SRI",
    "Name": "Sri Lanka"
  },
  {
    "Id": 203,
    "Code": "SUD",
    "Name": "Sudan"
  },
  {
    "Id": 204,
    "Code": "SUR",
    "Name": "Suriname"
  },
  {
    "Id": 206,
    "Code": "SWZ",
    "Name": "Swaziland"
  },
  {
    "Id": 207,
    "Code": "SWE",
    "Name": "Sweden"
  },
  {
    "Id": 208,
    "Code": "SUI",
    "Name": "Switzerland"
  },
  {
    "Id": 209,
    "Code": "SYR",
    "Name": "Syrian Arab Republic"
  },
  {
    "Id": 210,
    "Code": "TPE",
    "Name": "Taiwan"
  },
  {
    "Id": 211,
    "Code": "TJK",
    "Name": "Tajikistan"
  },
  {
    "Id": 212,
    "Code": "TAN",
    "Name": "Tanzania, United Republic of"
  },
  {
    "Id": 213,
    "Code": "THA",
    "Name": "Thailand"
  },
  {
    "Id": 214,
    "Code": "TLS",
    "Name": "Timor-Leste"
  },
  {
    "Id": 215,
    "Code": "TOG",
    "Name": "Togo"
  },
  {
    "Id": 217,
    "Code": "TGA",
    "Name": "Tonga"
  },
  {
    "Id": 218,
    "Code": "TRI",
    "Name": "Trinidad and Tobago"
  },
  {
    "Id": 219,
    "Code": "TUN",
    "Name": "Tunisia"
  },
  {
    "Id": 220,
    "Code": "TUR",
    "Name": "Turkey"
  },
  {
    "Id": 221,
    "Code": "TKM",
    "Name": "Turkmenistan"
  },
  {
    "Id": 223,
    "Code": "TUV",
    "Name": "Tuvalu"
  },
  {
    "Id": 224,
    "Code": "UGA",
    "Name": "Uganda"
  },
  {
    "Id": 225,
    "Code": "UKR",
    "Name": "Ukraine"
  },
  {
    "Id": 226,
    "Code": "UAE",
    "Name": "United Arab Emirates"
  },
  {
    "Id": 247,
    "Code": "GBR",
    "Name": "United Kingdom"
  },
  {
    "Id": 227,
    "Code": "USA",
    "Name": "United States"
  },
  {
    "Id": 229,
    "Code": "URU",
    "Name": "Uruguay"
  },
  {
    "Id": 230,
    "Code": "UZB",
    "Name": "Uzbekistan"
  },
  {
    "Id": 231,
    "Code": "VAN",
    "Name": "Vanuatu"
  },
  {
    "Id": 232,
    "Code": "VEN",
    "Name": "Venezuela"
  },
  {
    "Id": 233,
    "Code": "VIE",
    "Name": "Viet Nam"
  },
  {
    "Id": 234,
    "Code": "IVB",
    "Name": "Virgin Islands, British"
  },
  {
    "Id": 235,
    "Code": "ISV",
    "Name": "Virgin Islands, U.S."
  },
  {
    "Id": 238,
    "Code": "YEM",
    "Name": "Yemen"
  },
  {
    "Id": 239,
    "Code": "ZAM",
    "Name": "Zambia"
  },
  {
    "Id": 240,
    "Code": "ZIM",
    "Name": "Zimbabwe"
  }
]